{"title":"机器学习","date":"2015-12-20T12:10:16.000Z","excerpt":"","slug":"机器学习","comments":true,"tags":["机器学习"],"categories":["求知"],"updated":"2018-07-03T17:15:45.000Z","content":"<p><img src=\"http://www.kuqin.com/upimg/allimg/110727/22144S115-2.jpg\" alt=\"\"></p>\n","prev":{"title":"论文速读《On-line Active Reward Learning for Policy Optimisation in Spoken Dialogue Systems》","slug":"On-line Active Reward Learning for Policy Optimisation in Spoken Dialogue Systems"},"next":{"title":"reading","slug":"reading"},"link":"http://yoursite.com/post/机器学习"}