{"title":"论文速读《Two are Better than One An Ensemble of Retrieval and Generation-Based Dialog》","date":"2016-11-09T16:00:00.000Z","excerpt":"","slug":"Two are  Better than One An Ensemble of Retrieval and Generation-Based Dialog","comments":true,"tags":["RL","NLG"],"updated":"2016-11-28T06:25:42.000Z","content":"<h2 id=\"作者\"><a href=\"#作者\" class=\"headerlink\" title=\"作者\"></a>作者</h2><p>Yiping Song, Rui Yan, Xiang Li, Dongyan Zhao, Ming Zhang</p>\n<h2 id=\"单位\"><a href=\"#单位\" class=\"headerlink\" title=\"单位\"></a>单位</h2><p>北京大学</p>\n<h2 id=\"关键词\"><a href=\"#关键词\" class=\"headerlink\" title=\"关键词\"></a>关键词</h2><p>对话系统、open domain、chatbot</p>\n<h2 id=\"文章来源\"><a href=\"#文章来源\" class=\"headerlink\" title=\"文章来源\"></a>文章来源</h2><p>arXiv</p>\n<h2 id=\"问题\"><a href=\"#问题\" class=\"headerlink\" title=\"问题\"></a>问题</h2><p>对话系统中可将问题和检索的结果同时作为输入Encoder之后进行解码Decoder，再将生成的结果和原检索结果重排序</p>\n<h2 id=\"模型\"><a href=\"#模型\" class=\"headerlink\" title=\"模型\"></a>模型</h2><p><img src=\"http://7xpodp.com1.z0.glb.clouddn.com/blog/20161123/233005658.png\" alt=\"\"><br><img src=\"http://7xpodp.com1.z0.glb.clouddn.com/blog/20161123/233024296.png\" alt=\"\"></p>\n<h2 id=\"相关工作\"><a href=\"#相关工作\" class=\"headerlink\" title=\"相关工作\"></a>相关工作</h2><p><img src=\"http://7xpodp.com1.z0.glb.clouddn.com/blog/20161123/233041282.png\" alt=\"\"><br><img src=\"http://7xpodp.com1.z0.glb.clouddn.com/blog/20161123/233053949.png\" alt=\"\"></p>\n<h2 id=\"简评\"><a href=\"#简评\" class=\"headerlink\" title=\"简评\"></a>简评</h2><p>作者的思路非常简单，原来的回复生成模型容易发生回复内容短或者回复信息无意义的问题，在此作者将候选结果和原来的问句同时作为RNN生成器的输入，生成结果后再将本次生成的结果加入原检索候选集中，进行重新排序，实验结果证明此种方法比单独使用检索或单独使用生成效果有大幅提升。</p>\n","prev":{"title":"论文速读《Learning to compose words into sentences with reinforcement learning》","slug":"Learning to compose words into sentences with reinforcement learning_Tonya"},"next":{"title":"powerline配置","slug":"powerline配置"},"link":"http://yoursite.com/post/Two are  Better than One An Ensemble of Retrieval and Generation-Based Dialog","toc":[{"title":"作者","id":"作者","index":"1"},{"title":"单位","id":"单位","index":"2"},{"title":"关键词","id":"关键词","index":"3"},{"title":"文章来源","id":"文章来源","index":"4"},{"title":"问题","id":"问题","index":"5"},{"title":"模型","id":"模型","index":"6"},{"title":"相关工作","id":"相关工作","index":"7"},{"title":"简评","id":"简评","index":"8"}]}